so2sql/__init__.py
so2sql/models.py
so2sql/so2sql.py
so2sql/sqldf.py
so2sql/utils.py
tests/__init__.py
tests/mockresponses.py
tests/test_so2sql.py
tests/test_sqldf.py
tests/test_utils.py
so2sql-0.0.14.dist-info/METADATA
so2sql-0.0.14.dist-info/WHEEL
so2sql-0.0.14.dist-info/top_level.txt
so2sql-0.0.14.dist-info/RECORD
